{"topic":{"24":"blockchain","70":"blockchain","25":"blockchain","71":"blockchain","26":"blockchain","72":"blockchain","27":"blockchain","73":"blockchain","28":"blockchain","74":"blockchain","29":"blockchain","75":"blockchain","30":"blockchain","76":"blockchain","31":"blockchain","77":"blockchain","32":"blockchain"},"youtube_link":{"24":"https:\/\/youtu.be\/hYip_Vuv8J0?t=388","70":"https:\/\/youtu.be\/hYip_Vuv8J0","25":"https:\/\/youtu.be\/hYip_Vuv8J0?t=388","71":"https:\/\/youtu.be\/hYip_Vuv8J0","26":"https:\/\/youtu.be\/hYip_Vuv8J0?t=388","72":"https:\/\/youtu.be\/hYip_Vuv8J0","27":"https:\/\/youtu.be\/hYip_Vuv8J0?t=388","73":"https:\/\/youtu.be\/hYip_Vuv8J0","28":"https:\/\/youtu.be\/hYip_Vuv8J0?t=388","74":"https:\/\/youtu.be\/hYip_Vuv8J0","29":"https:\/\/youtu.be\/hYip_Vuv8J0?t=388","75":"https:\/\/youtu.be\/hYip_Vuv8J0","30":"https:\/\/youtu.be\/hYip_Vuv8J0?t=388","76":"https:\/\/youtu.be\/hYip_Vuv8J0","31":"https:\/\/youtu.be\/hYip_Vuv8J0?t=388","77":"https:\/\/youtu.be\/hYip_Vuv8J0","32":"https:\/\/youtu.be\/hYip_Vuv8J0?t=388"},"wired_link":{"24":"https:\/\/www.wired.com\/video\/watch\/expert-explains-one-concept-in-5-levels-of-difficulty-blockchain","70":"https:\/\/www.wired.com\/video\/watch\/expert-explains-one-concept-in-5-levels-of-difficulty-blockchain","25":"https:\/\/www.wired.com\/video\/watch\/expert-explains-one-concept-in-5-levels-of-difficulty-blockchain","71":"https:\/\/www.wired.com\/video\/watch\/expert-explains-one-concept-in-5-levels-of-difficulty-blockchain","26":"https:\/\/www.wired.com\/video\/watch\/expert-explains-one-concept-in-5-levels-of-difficulty-blockchain","72":"https:\/\/www.wired.com\/video\/watch\/expert-explains-one-concept-in-5-levels-of-difficulty-blockchain","27":"https:\/\/www.wired.com\/video\/watch\/expert-explains-one-concept-in-5-levels-of-difficulty-blockchain","73":"https:\/\/www.wired.com\/video\/watch\/expert-explains-one-concept-in-5-levels-of-difficulty-blockchain","28":"https:\/\/www.wired.com\/video\/watch\/expert-explains-one-concept-in-5-levels-of-difficulty-blockchain","74":"https:\/\/www.wired.com\/video\/watch\/expert-explains-one-concept-in-5-levels-of-difficulty-blockchain","29":"https:\/\/www.wired.com\/video\/watch\/expert-explains-one-concept-in-5-levels-of-difficulty-blockchain","75":"https:\/\/www.wired.com\/video\/watch\/expert-explains-one-concept-in-5-levels-of-difficulty-blockchain","30":"https:\/\/www.wired.com\/video\/watch\/expert-explains-one-concept-in-5-levels-of-difficulty-blockchain","76":"https:\/\/www.wired.com\/video\/watch\/expert-explains-one-concept-in-5-levels-of-difficulty-blockchain","31":"https:\/\/www.wired.com\/video\/watch\/expert-explains-one-concept-in-5-levels-of-difficulty-blockchain","77":"https:\/\/www.wired.com\/video\/watch\/expert-explains-one-concept-in-5-levels-of-difficulty-blockchain","32":"https:\/\/www.wired.com\/video\/watch\/expert-explains-one-concept-in-5-levels-of-difficulty-blockchain"},"dialog_lvl":{"24":"grad","70":"grad","25":"grad","71":"grad","26":"grad","72":"grad","27":"grad","73":"grad","28":"grad","74":"grad","29":"grad","75":"grad","30":"grad","76":"grad","31":"grad","77":"grad","32":"grad"},"dialog_id":{"24":"blockchain_6","70":"blockchain_6","25":"blockchain_6","71":"blockchain_6","26":"blockchain_6","72":"blockchain_6","27":"blockchain_6","73":"blockchain_6","28":"blockchain_6","74":"blockchain_6","29":"blockchain_6","75":"blockchain_6","30":"blockchain_6","76":"blockchain_6","31":"blockchain_6","77":"blockchain_6","32":"blockchain_6"},"speaker_id":{"24":1,"70":5,"25":1,"71":5,"26":1,"72":5,"27":1,"73":5,"28":1,"74":5,"29":1,"75":5,"30":1,"76":5,"31":1,"77":5,"32":1},"reciever_id":{"24":5,"70":1,"25":5,"71":1,"26":5,"72":1,"27":5,"73":1,"28":5,"74":1,"29":5,"75":1,"30":5,"76":1,"31":5,"77":1,"32":5},"turn_id":{"24":1,"70":2,"25":3,"71":4,"26":5,"72":6,"27":7,"73":8,"28":9,"74":10,"29":11,"75":12,"30":13,"76":14,"31":15,"77":16,"32":17},"turn":{"24":["So today, we're gonna talk about blockchain technology."],"70":["Okay."],"25":["[Bettina] Have you ever heard of blockchain?"],"71":["I have.","Whenever we have a transaction, and let's say","I buy something from you, this information gets logged.","And it gets verified by a third person or third party.","And then if like all this information verified","and it all matches, right, the transaction goes through","without any intermediary basically, right?","It gets stored, and when you make further transactions,","this information is ready, embedded.","It's in the ledger."],"26":["Yeah, that's exactly right.","And you can append it.","You can sort of add new information that's more current,","but you can't actually go erase anything."],"72":["Absolutely.","The way the technology's changing,","nothing's gonna be like it used to be.","And there's no like firm, and then the buyer","and the seller, it basically, we'll have","to rewrite a lot of rules in economics as well."],"27":["For sure.","A lot of the assumptions won't hold true."],"73":["Absolutely."],"28":["Same with, who are the actors?","It's not just people anymore.","It's machines."],"74":["[Valentinas] Absolutely."],"29":["We're gonna have to create entire new concepts","of how they do trade and how they work with us, too.","What kind of barriers or road blocks would you imagine","are gonna happen in the blockchain space?"],"75":["So at least when we talk about Bitcoin,","there are some trust issues and some hacks.","So there's obviously a need to work on trust","and feeling that it's a safe technology."],"30":["Yeah.","One of the problems that Bitcoin has faced","is Bitcoins getting stolen or lost.","But a lot of that actually comes from people","trying to recentralize Bitcoin in different ways","making themselves actually a pretty easy target."],"76":["Absolutely, so education will be a big part","before we actually can use the technology in a wide sense.","Right?"],"31":["Yeah.","To actually transition into the mainstream","and make it useful for average people to use,","we're going to need to make sure we have","a lot more education, a lot more standards","and probably work with a lot of enterprises","to create sort of a user experience around","this being a technology that is safe","and usable and understandable.","What is the current state of blockchain","in your understanding?","What's gonna have to happen next?"],"77":["The current state is in the research state,","and it's being developed to be applied in many, many areas.","It must be used almost everywhere","to where we won't even imagine how we lived without it.","But I'm not sure where it's going to go.","I mean, no one really knows, right."],"32":["Well, we have a lot of public blockchains.","Like we have Bitcoin.","We have the Ethereum network and XT,","but a lot of companies and consortiums","are getting together to build private blockchains,","so ones that are more closed off at first","and then may evolve into a public network","where people feel comfortable using it.","And some are also proof of concept out in the real world,","projects in energy and in pharmaceuticals","and in retail and lots of different fields","are starting experiments.","And we'll see in the next few years","how all of those interact and what we learn","about the best use cases for blockchain","and what it means for trade."]},"turn_sentences":{"24":["So today, we're gonna talk about blockchain technology."],"70":["Okay."],"25":["[Bettina] Have you ever heard of blockchain?"],"71":["I have.","Whenever we have a transaction, and let's say I buy something from you, this information gets logged.","And it gets verified by a third person or third party.","And then if like all this information verified and it all matches, right, the transaction goes through without any intermediary basically, right?","It gets stored, and when you make further transactions, this information is ready, embedded.","It's in the ledger."],"26":["Yeah, that's exactly right.","And you can append it.","You can sort of add new information that's more current, but you can't actually go erase anything."],"72":["Absolutely.","The way the technology's changing, nothing's gonna be like it used to be.","And there's no like firm, and then the buyer and the seller, it basically, we'll have to rewrite a lot of rules in economics as well."],"27":["For sure.","A lot of the assumptions won't hold true."],"73":["Absolutely."],"28":["Same with, who are the actors?","It's not just people anymore.","It's machines."],"74":["[Valentinas] Absolutely."],"29":["We're gonna have to create entire new concepts of how they do trade and how they work with us, too.","What kind of barriers or road blocks would you imagine are gonna happen in the blockchain space?"],"75":["So at least when we talk about Bitcoin, there are some trust issues and some hacks.","So there's obviously a need to work on trust and feeling that it's a safe technology."],"30":["Yeah.","One of the problems that Bitcoin has faced is Bitcoins getting stolen or lost.","But a lot of that actually comes from people trying to recentralize Bitcoin in different ways making themselves actually a pretty easy target."],"76":["Absolutely, so education will be a big part before we actually can use the technology in a wide sense.","Right?"],"31":["Yeah.","To actually transition into the mainstream and make it useful for average people to use, we're going to need to make sure we have a lot more education, a lot more standards and probably work with a lot of enterprises to create sort of a user experience around this being a technology that is safe and usable and understandable.","What is the current state of blockchain in your understanding?","What's gonna have to happen next?"],"77":["The current state is in the research state, and it's being developed to be applied in many, many areas.","It must be used almost everywhere to where we won't even imagine how we lived without it.","But I'm not sure where it's going to go.","I mean, no one really knows, right."],"32":["Well, we have a lot of public blockchains.","Like we have Bitcoin.","We have the Ethereum network and XT, but a lot of companies and consortiums are getting together to build private blockchains, so ones that are more closed off at first and then may evolve into a public network where people feel comfortable using it.","And some are also proof of concept out in the real world, projects in energy and in pharmaceuticals and in retail and lots of different fields are starting experiments.","And we'll see in the next few years how all of those interact and what we learn about the best use cases for blockchain and what it means for trade."]},"turn_num_tokens":{"24":12,"70":2,"25":10,"71":86,"26":34,"72":52,"27":13,"73":2,"28":19,"74":5,"29":43,"75":37,"30":41,"76":23,"31":85,"77":64,"32":125},"role":{"24":"Explainer","70":"Explainee","25":"Explainer","71":"Explainee","26":"Explainer","72":"Explainee","27":"Explainer","73":"Explainee","28":"Explainer","74":"Explainee","29":"Explainer","75":"Explainee","30":"Explainer","76":"Explainee","31":"Explainer","77":"Explainee","32":"Explainer"}}